LICENSE
MANIFEST.in
README.rst
pyproject.toml
setup.cfg
setup.py
django_lb_workflow.egg-info/PKG-INFO
django_lb_workflow.egg-info/SOURCES.txt
django_lb_workflow.egg-info/dependency_links.txt
django_lb_workflow.egg-info/requires.txt
django_lb_workflow.egg-info/top_level.txt
lbworkflow/__init__.py
lbworkflow/admin.py
lbworkflow/apps.py
lbworkflow/forms.py
lbworkflow/settings.py
lbworkflow/urls.py
lbworkflow/wfdata.py
lbworkflow/core/__init__.py
lbworkflow/core/datahelper.py
lbworkflow/core/exceptions.py
lbworkflow/core/helper.py
lbworkflow/core/sendmsg.py
lbworkflow/core/transition.py
lbworkflow/core/userparser.py
lbworkflow/flowgen/__init__.py
lbworkflow/flowgen/app_template/__init__.py-tpl
lbworkflow/flowgen/app_template/admin.py-tpl
lbworkflow/flowgen/app_template/forms.py-tpl
lbworkflow/flowgen/app_template/views.py-tpl
lbworkflow/flowgen/app_template/wf_views.py-tpl
lbworkflow/flowgen/app_template/wfdata.py-tpl
lbworkflow/flowgen/app_template/templates/app_name/detail.html-tpl
lbworkflow/flowgen/app_template/templates/app_name/form.html-tpl
lbworkflow/flowgen/app_template/templates/app_name/inc_detail_info.html-tpl
lbworkflow/flowgen/app_template/templates/app_name/list.html-tpl
lbworkflow/flowgen/app_template/templates/app_name/print.html-tpl
lbworkflow/migrations/0001_initial.py
lbworkflow/migrations/0002_auto_20171019_0549.py
lbworkflow/migrations/0003_auto_20200221_0438.py
lbworkflow/migrations/0004_processreportlink_uuid.py
lbworkflow/migrations/0005_auto_20211217_0304.py
lbworkflow/migrations/__init__.py
lbworkflow/models/__init__.py
lbworkflow/models/config.py
lbworkflow/models/runtime.py
lbworkflow/simplewf/__init__.py
lbworkflow/simplewf/admin.py
lbworkflow/simplewf/forms.py
lbworkflow/simplewf/models.py
lbworkflow/simplewf/views.py
lbworkflow/simplewf/wfdata.py
lbworkflow/simplewf/migrations/0001_initial.py
lbworkflow/simplewf/migrations/0002_alter_simpleworkflow_id.py
lbworkflow/simplewf/migrations/__init__.py
lbworkflow/simplewf/templates/simplewf/detail.html
lbworkflow/simplewf/templates/simplewf/form.html
lbworkflow/simplewf/templates/simplewf/inc_detail_info.html
lbworkflow/simplewf/templates/simplewf/list.html
